snowconvert_export_tera-0.0.18.data/scripts/sc-tera-export
snowconvert_export_tera-0.0.18.data/scripts/sc-tera-extract-snippets
snowconvert_export_tera-0.0.18.data/scripts/sc-tera-restore-snippets
snowconvert_export_tera-0.0.18.data/scripts/sc-tera-split-ddl
split/__init__.py
split/__main__.py
teraexport/__init__.py
teraexport/__main__.py
teraexport/bin/create_ddls.sh
teraexport/bin/create_load_to_sf.sh
teraexport/scripts/create_ddls.btq
teraexport/scripts/create_reports.btq
teraexport/scripts/create_sample_inserts.btq
teraexport/scripts/create_tpt_script.btq
teraexport/scripts/create_usage_reports.btq
teraexport/scripts/data_profiling.btq
teraexport/scripts/invalid_objects.btq
snowconvert_export_tera-0.0.18.dist-info/LICENSE.txt
snowconvert_export_tera-0.0.18.dist-info/METADATA
snowconvert_export_tera-0.0.18.dist-info/WHEEL
snowconvert_export_tera-0.0.18.dist-info/top_level.txt
snowconvert_export_tera-0.0.18.dist-info/RECORD
